rinse-0.4.0.dist-info/pbr.json
rinse-0.4.0.dist-info/METADATA
rinse-0.4.0.dist-info/top_level.txt
rinse-0.4.0.dist-info/DESCRIPTION.rst
rinse-0.4.0.dist-info/metadata.json
rinse-0.4.0.dist-info/WHEEL
rinse-0.4.0.dist-info/RECORD
rinse/wsdl.py
rinse/wsa.py
rinse/client.py
rinse/message.py
rinse/wsse.py
rinse/xsd.py
rinse/util.py
rinse/__init__.py
rinse/response.py
rinse/tests/utils.py
rinse/tests/test_client.py
rinse/tests/__init__.py
rinse/res/soap-1.2.xsd
rinse/res/soap-1.1_envelope.xsd
rinse/res/soap-1.1.xsd
