Metadata-Version: 2.0
Name: rinse
Version: 0.4.0
Summary: SOAP client built with lxml and requests.
Home-page: https://rinse.readthedocs.org/en/latest/
Author: Tyson Clugg
Author-email: tyson@clugg.net
License: MIT
Platform: UNKNOWN
Classifier: Development Status :: 4 - Beta
Classifier: Intended Audience :: Developers
Classifier: Topic :: Communications
Classifier: Topic :: Internet
Classifier: Topic :: Internet :: WWW/HTTP
Classifier: Topic :: Internet :: WWW/HTTP :: Dynamic Content
Classifier: Topic :: Software Development :: Libraries
Classifier: Topic :: Text Processing :: Markup :: XML
Classifier: License :: OSI Approved :: MIT License
Classifier: License :: DFSG approved
Classifier: License :: OSI Approved
Classifier: Programming Language :: Python
Classifier: Programming Language :: Python :: 2
Classifier: Programming Language :: Python :: 3
Classifier: Framework :: Django
Classifier: Programming Language :: Python :: 2.7
Classifier: Programming Language :: Python :: 3.3
Classifier: Programming Language :: Python :: 3.4
Classifier: Framework :: Django :: 1.7
Classifier: Framework :: Django :: 1.8
Requires-Dist: defusedxml
Requires-Dist: lxml
Requires-Dist: requests
